{"urlid":"150","title":"站在巨人的肩膀上写代码—SPL","categary":"后端开发","coursetype":"PHP","nd":"高级","wt":" 3小时30分","description":"简介：通过本课程的学习，可以了解SPL的概念，掌握SPL的常用类、接口、数据结构和函数，再通过案例的讲解学习，掌握相应的知识点和技能，能灵活运用案例代码提高实际工作的效率。","chapters":[{"title":"第1章SPL简介","citems":[{"title":"1-1课程概述(09:15)开始学习","type":"video/","id":"2510"}]},{"title":"第2章SPL的常用数据结构","citems":[{"title":"2-1SPL数据结构简介(07:02)开始学习","type":"video/","id":"2511"},{"title":"2-2SPL数据结构之双向链表简介(08:50)开始学习","type":"video/","id":"2512"},{"title":"2-3SPL数据结构之SplDoublyLinkedList类(04:06)开始学习","type":"video/","id":"2514"},{"title":"2-4SPL数据结构之双向链表的代码实现(28:30)开始学习","type":"video/","id":"2515"},{"title":"2-5SPL数据结构之双向链表小结(02:56)开始学习","type":"video/","id":"2516"},{"title":"2-6SPL数据结构之堆栈的简介(03:18)开始学习","type":"video/","id":"2517"},{"title":"2-7SPL数据结构之堆栈的代码实现(15:38)开始学习","type":"video/","id":"2518"},{"title":"2-8SPL数据结构之队列(09:32)开始学习","type":"video/","id":"2519"}]},{"title":"第3章SPL的常用迭代器","citems":[{"title":"3-1SPL迭代器概述(02:39)开始学习","type":"video/","id":"2595"},{"title":"3-2ArrayIterator迭代器(15:47)开始学习","type":"video/","id":"2600"},{"title":"3-3AppendIterator迭代器(03:38)开始学习","type":"video/","id":"2601"},{"title":"3-4MultipleIterator迭代器(07:44)开始学习","type":"video/","id":"2603"},{"title":"3-5FilesystemIterator迭代器(10:34)开始学习","type":"video/","id":"2604"}]},{"title":"第4章SPL的基础接口","citems":[{"title":"4-1SPL接口简介(02:40)开始学习","type":"video/","id":"2614"},{"title":"4-2Countable接口(07:35)开始学习","type":"video/","id":"2615"},{"title":"4-3OuterIterator接口(06:51)开始学习","type":"video/","id":"2616"},{"title":"4-4RecursiveIterator接口(01:48)开始学习","type":"video/","id":"2617"},{"title":"4-5SeekableIterator接口(02:15)开始学习","type":"video/","id":"2618"}]},{"title":"第5章SPL函数的使用","citems":[{"title":"5-1SPL使用spl_autoload_register函数装载类(10:03)开始学习","type":"video/","id":"2620"},{"title":"5-2SPL使用__autoload装载类(07:23)开始学习","type":"video/","id":"2621"},{"title":"5-3SPL通过自定义的__autoload函数装载类(05:05)开始学习","type":"video/","id":"2622"},{"title":"5-4SPL其他函数(06:35)开始学习","type":"video/","id":"2623"}]},{"title":"第6章SPL的文件处理类库","citems":[{"title":"6-1SPL的文件处理类库(06:31)开始学习","type":"video/","id":"2625"},{"title":"6-2课程总结(01:53)开始学习","type":"video/","id":"2626"}]}]}