{"urlid":"338","title":"canvas实现星星闪烁特效","categary":"前端开发","coursetype":"Html5","nd":"中级","wt":" 1小时15分","description":"简介：通过制作一个用鼠标事件控制的小案例，学会使用基于canvas画布的各种绘图方法，通过灵活使用一些绘图方法的各项参数达到一些特殊效果。在课程中还将讲述如何将一个复杂的问题进行拆解，逐步实现目标的方法。","chapters":[{"title":"第1章前期准备","citems":[{"title":"1-1课程简介(04:49)开始学习","type":"video/","id":"6524"},{"title":"1-2网页结构搭建(01:52)开始学习","type":"video/","id":"6525"}]},{"title":"第2章代码编写","citems":[{"title":"2-1页面代码编写(06:53)开始学习","type":"video/","id":"6526"},{"title":"2-2如何循环调用方法总结(05:03)开始学习","type":"video/","id":"6527"},{"title":"2-3绘制女孩图片(04:24)开始学习","type":"video/","id":"6528"},{"title":"2-4闪烁星星动画分析(01:50)开始学习","type":"video/","id":"6529"},{"title":"2-5随机生成很多星星(08:15)开始学习","type":"video/","id":"6530"},{"title":"2-6星星闪烁动画(12:09)开始学习","type":"video/","id":"6531"},{"title":"2-7星星重生判断(07:52)开始学习","type":"video/","id":"6532"},{"title":"2-8鼠标控制事件（1）(07:01)开始学习","type":"video/","id":"6533"},{"title":"2-9鼠标控制事件（2）(04:22)开始学习","type":"video/","id":"6535"},{"title":"2-10鼠标控制事件（3）(04:02)开始学习","type":"video/","id":"6536"}]},{"title":"第3章课程总结","citems":[{"title":"3-1课程总结(03:55)开始学习","type":"video/","id":"6537"},{"title":"3-2思考题(01:27)开始学习","type":"video/","id":"6538"}]}]}