{"urlid":"476","title":"Canvas玩转图像处理","categary":"前端开发","coursetype":"Html5","nd":"高级","wt":" 1小时58分","description":"简介：canvas为开发者们提供了激动人心的图像操作方法，让我们一起来看看，我们都能使用这些方法，如何使用canvas玩转图像处理吧！","chapters":[{"title":"第1章欢迎进入Canvas的图像世界","citems":[{"title":"1-1欢迎进入Canvas的图像世界(05:45)开始学习","type":"video/","id":"9263"}]},{"title":"第2章Canvas图像基础","citems":[{"title":"2-1Canvas基础使用drawImage绘制图像(08:29)开始学习","type":"video/","id":"9274"},{"title":"2-2Canvas基础玩转drawImage的参数(05:42)开始学习","type":"video/","id":"9275"},{"title":"2-3Canvas基础在画布中心缩放图像(15:01)开始学习","type":"video/","id":"9277"},{"title":"2-4Canvas基础使用滑杆交互(04:56)开始学习","type":"video/","id":"9300"}]},{"title":"第3章离屏Canvas","citems":[{"title":"3-1离屏Canvas为图片添加水印(09:09)开始学习","type":"video/","id":"9285"},{"title":"3-2canvas和鼠标交互(11:37)开始学习","type":"video/","id":"9281"},{"title":"3-3使用离屏Canvas制作放大镜效果(10:39)开始学习","type":"video/","id":"9282"},{"title":"3-4离屏Canvas使用剪辑区域优化(05:02)开始学习","type":"video/","id":"9283"}]},{"title":"第4章使用Canvas进行像素级操作","citems":[{"title":"4-1getImageData和putImageData(09:01)开始学习","type":"video/","id":"9284"},{"title":"4-2Canvas创建属于自己的滤镜效果(05:34)开始学习","type":"video/","id":"9301"},{"title":"4-3Canvas更复杂的滤镜效果(19:49)开始学习","type":"video/","id":"9287"},{"title":"4-4Canvas创建ImageData，感受图像之美(06:48)开始学习","type":"video/","id":"9288"}]}]}