{"urlid":"477","title":"C++远征之模板篇","categary":"后端开发","coursetype":"C++","nd":"初级","wt":" 3小时21分","description":"简介：本课程将带领大家体会更为奇妙的C++，讲述了静态、友元、运算符重载的定义及使用方法，其中重点讲述函数模板、类模板以及标准模板库的相关知识，知识内容更重实用性，本门课程对于面向对象的语言的学习将大有裨益，所有知识均以实践的方式讲解到操作层面，力求即学即会。","chapters":[{"title":"第1章课程介绍","citems":[{"title":"1-1课程简介(02:40)开始学习","type":"video/","id":"9581"}]},{"title":"第2章友元函数和友元类","citems":[{"title":"2-1[C++]友元函数(07:44)开始学习","type":"video/","id":"9582"},{"title":"2-2[C++]友元函数编码实现(08:56)开始学习","type":"video/","id":"9583"},{"title":"2-3单元巩固开始学习","type":"code/","id":"9675"},{"title":"2-4[C++]友元类(03:51)开始学习","type":"video/","id":"9584"},{"title":"2-5[C++]友元类编码实现(05:07)开始学习","type":"video/","id":"9585"},{"title":"2-6单元巩固开始学习","type":"code/","id":"9676"},{"title":"2-7练习题开始学习","type":"code/"}]},{"title":"第3章static","citems":[{"title":"3-1[C++]静态(10:08)开始学习","type":"video/","id":"9586"},{"title":"3-2[C++]静态编码实现(10:49)开始学习","type":"video/","id":"9587"},{"title":"3-3练习题开始学习","type":"code/"}]},{"title":"第4章运算符重载","citems":[{"title":"4-1[C++]一元运算符重载(10:07)开始学习","type":"video/","id":"9588"},{"title":"4-2[C++]一元运算符编码实现（一）(11:25)开始学习","type":"video/","id":"9589"},{"title":"4-3[C++]一元运算符编码实现（二）(09:01)开始学习","type":"video/","id":"9590"},{"title":"4-4[C++]二元运算符重载(12:39)开始学习","type":"video/","id":"9591"},{"title":"4-5[C++]二次运算符重载编码实现(12:03)开始学习","type":"video/","id":"9592"},{"title":"4-6练习题开始学习","type":"code/"},{"title":"4-7综合练习开始学习","type":"code/","id":"9674"}]},{"title":"第5章模板函数与模板类","citems":[{"title":"5-1[C++]函数模板(11:25)开始学习","type":"video/","id":"9593"},{"title":"5-2[C++]函数模板编码实现(06:38)开始学习","type":"video/","id":"9594"},{"title":"5-3练习题开始学习","type":"code/"},{"title":"5-4单元巩固开始学习","type":"code/","id":"9670"},{"title":"5-5[C++]类模板(04:59)开始学习","type":"video/","id":"9595"},{"title":"5-6[C++]类模板编码实现(05:52)开始学习","type":"video/","id":"9596"},{"title":"5-7练习题开始学习","type":"code/"},{"title":"5-8单元巩固开始学习","type":"code/","id":"9671"}]},{"title":"第6章标准模板类","citems":[{"title":"6-1[C++]标准模板库(16:42)开始学习","type":"video/","id":"9597"},{"title":"6-2[C++]标准模板库编码实现（一）(08:19)开始学习","type":"video/","id":"9598"},{"title":"6-3[C++]标准模板库编码实现（二）(12:21)开始学习","type":"video/","id":"9599"},{"title":"6-4练习题开始学习","type":"code/"},{"title":"6-5单元巩固开始学习","type":"code/","id":"9672"}]}]}