{"urlid":"57","title":"如何用CSS进行网页布局","categary":"前端开发","coursetype":"HTML/CSS","nd":"中级","wt":"22分","description":"简介：如何用CSS进行网页布局？这可是前端工程师最最基本的技能，本课程教你怎么制作一列布局、二列布局、三列布局当然还有最通用的混合布局，而且你还可以选择让它固定还是自适应。用CSS重新规划你的网页，让你的网页从此更美观、更友好。","chapters":[{"title":"第1章内容简介","citems":[{"title":"1-1内容简介(04:47)开始学习","type":"video/","id":"771"}]},{"title":"第2章用HTML+CSS实现最简单的网页布局效果：一列布局","citems":[{"title":"2-1一列布局(04:09)开始学习","type":"video/","id":"772"},{"title":"2-2练习题开始学习","type":"code/"},{"title":"2-3编程练习开始学习","type":"code/","id":"1078"}]},{"title":"第3章自适应宽度及固定宽度的二列布局的实现","citems":[{"title":"3-1二列布局(03:06)开始学习","type":"video/","id":"773"},{"title":"3-2评测题目开始学习","type":"code/"},{"title":"3-3编程练习开始学习","type":"code/","id":"1079"}]},{"title":"第4章用position定位方法实现自适应效果的三列布局","citems":[{"title":"4-1三列布局(03:21)开始学习","type":"video/","id":"774"},{"title":"4-3编程练习开始学习","type":"code/","id":"1080"}]},{"title":"第5章用HTML+CSS实现复杂结构的混合布局","citems":[{"title":"5-1混合布局(05:24)开始学习","type":"video/","id":"775"},{"title":"5-2实践题开始学习","type":"code/","id":"1081"},{"title":"5-3编程挑战开始学习","type":"code/","id":"1409"}]}]}