{"urlid":"789","title":"Angular2一小时快速入门","categary":"前端开发","coursetype":"AngularJS","nd":"中级","wt":" 1小时11分","description":"简介：Angular2 于2016年9月份正式发布，功能特性趋于稳定，本课程基于 Angular2 正式版展开，共分为三个章节：第一章简述 Angular 的发展历史；第二章详解Angular2 的八个核心概念；第三章通过由浅入深的代码实操再次加深对 Angular2的理解，帮助大家快速上手 Angular2 开发。","chapters":[{"title":"第1章Angular的发展历史","citems":[{"title":"1-1Angular起源(02:35)开始学习","type":"video/","id":"14300"},{"title":"1-2AngularJS的痛点(03:11)开始学习","type":"video/","id":"14302"},{"title":"1-3Angular2特性(04:38)开始学习","type":"video/","id":"14303"}]},{"title":"第2章Angular2的核心概念详解","citems":[{"title":"2-1组件及组件树(12:02)开始学习","type":"video/","id":"14304"},{"title":"2-2指令(03:15)开始学习","type":"video/","id":"14305"},{"title":"2-3服务与依赖注入(05:05)开始学习","type":"video/","id":"14306"},{"title":"2-4模块(08:47)开始学习","type":"video/","id":"14307"}]},{"title":"第3章Angular2快速上手","citems":[{"title":"3-1TypeScript简述(04:23)开始学习","type":"video/","id":"14308"},{"title":"3-2开发环境准备(01:47)开始学习","type":"video/","id":"14309"},{"title":"3-3项目启动(08:14)开始学习","type":"video/","id":"14310"},{"title":"3-4内置指令使用(03:11)开始学习","type":"video/","id":"14311"},{"title":"3-5自定义指令使用(02:41)开始学习","type":"video/","id":"14312"},{"title":"3-6服务使用(02:19)开始学习","type":"video/","id":"14313"},{"title":"3-7父子组件通讯(08:10)开始学习","type":"video/","id":"14314"}]}]}